Workbook

Sheet Cruscotto
A1: Come stai andando
A2: Tutto qui dentro si calcola dai fogli Settimane, Spese e Piano. Non c'è niente da scrivere.
A4: Settimane registrate | B4: =COUNT(Settimane!$A$4:$A$203) | C4: Quante domeniche hai chiuso.
A5: Ultima domenica chiusa | B5: =IF($B$4=0,"",MAX(Settimane!$A$4:$A$203)) | C5: Se è più vecchia di una settimana, sei in ritardo.
A6: Fondo sul conto risparmio | B6: =IF($B$4=0,0,INDEX(Settimane!$C$4:$C$203,MATCH(MAX(Settimane!$A$4:$A$203),Settimane!$A$4:$A$203,0))) | C6: L'ultimo saldo che hai registrato.
A7: Obiettivo | B7: =Piano!$B$3 | C7: Il traguardo.
A8: Mancano al traguardo | B8: =MAX(0,$B$7-$B$6) | C8: Quanto resta da mettere via.
A9: Conto corrente | B9: =IF($B$4=0,0,INDEX(Settimane!$B$4:$B$203,MATCH(MAX(Settimane!$A$4:$A$203),Settimane!$A$4:$A$203,0))) | C9: L'ultimo saldo del conto operativo.
A10: Contanti | B10: =IF($B$4=0,0,INDEX(Settimane!$D$4:$D$203,MATCH(MAX(Settimane!$A$4:$A$203),Settimane!$A$4:$A$203,0))) | C10: L'ultimo contante dichiarato.
A11: Buoni pasto residui | B11: =IF($B$4=0,0,INDEX(Settimane!$E$4:$E$203,MATCH(MAX(Settimane!$A$4:$A$203),Settimane!$A$4:$A$203,0))) | C11: L'ultimo saldo EdenRed dichiarato.
A12: Buffer accantonato | B12: =IF($B$5="",0,Piano!$B$4*MAX(0,(YEAR($B$5)-YEAR(Piano!$B$5))*12+MONTH($B$5)-MONTH(Piano!$B$5)+1)) | C12: 150 € per ogni mese trascorso dall'inizio.
A13: Già speso dal buffer | B13: =Spese!$C$105 | C13: Somma del foglio Spese, incluse le righe previsto.
A14: Buffer disponibile | B14: =$B$12-$B$13 | C14: Se va sotto zero lo sta finanziando il fondo: normale con assicurazione e lotta insieme.
A15: Cassa libera | B15: =$B$9-MAX(0,$B$14) | C15: Sul conto corrente, tolto il buffer. È quello che puoi spendere davvero.
A16: Il piano a quella data | B16: =IF(NOT(ISNUMBER($B$5)),0,IF($B$5<=INDEX(Piano!$A$12:$A$14,1),0,IF($B$5>=INDEX(Piano!$A$12:$A$14,3),INDEX(Piano!$B$12:$B$14,3),INDEX(Piano!$B$12:$B$14,MATCH($B$5,Piano!$A$12:$A$14,1))+($B$5-INDEX(Piano!$A$12:$A$14,MATCH($B$5,Piano!$A$12:$A$14,1)))/(INDEX(Piano!$A$12:$A$14,MATCH($B$5,Piano!$A$12:$A$14,1)+1)-INDEX(Piano!$A$12:$A$14,MATCH($B$5,Piano!$A$12:$A$14,1)))*(INDEX(Piano!$B$12:$B$14,MATCH($B$5,Piano!$A$12:$A$14,1)+1)-INDEX(Piano!$B$12:$B$14,MATCH($B$5,Piano!$A$12:$A$14,1)))))) | C16: Dove dovresti essere secondo la curva del foglio Piano.
A17: Avanti (+) o indietro (−) sul piano | B17: =$B$6-$B$16 | C17: Positivo: sei in anticipo. Negativo: recupera.
A18: Speso l'ultima settimana | B18: =IF($B$4<2,"",INDEX(Settimane!$I$4:$I$203,MATCH(MAX(Settimane!$A$4:$A$203),Settimane!$A$4:$A$203,0))) | C18: Calcolato dai saldi, non dagli scontrini.
A19: Media delle ultime 4 settimane | B19: =IFERROR(AVERAGEIFS(Settimane!$I$4:$I$203,Settimane!$A$4:$A$203,">="&($B$5-21),Settimane!$A$4:$A$203,"<="&$B$5),"") | C19: Il numero da guardare: una settimana storta non vuol dire niente.
A20: Scarto vs budget, ultima settimana | B20: =IF($B$4<1,"",INDEX(Settimane!$K$4:$K$203,MATCH(MAX(Settimane!$A$4:$A$203),Settimane!$A$4:$A$203,0))) | C20: Dal foglio Settimane: negativo è buono, hai speso meno del previsto.
A23: Come si usa
A24: 1. | C24: Domenica sera apri l'app della banca, conta i contanti e leggi il saldo EdenRed.
A25: 2. | C25: Vai sul foglio Settimane, prima riga vuota, e scrivi data e i quattro saldi (celle blu).
A26: 3. | C26: Prima di chiudere la settimana, scrivi in «Budget previsto» quanto pensavi di spendere.
A27: 4. | C27: Se in settimana è entrato qualcosa — stipendio, ripetizioni, i soldi dei tuoi — scrivilo in «Entrate» e, se vuoi tenerne memoria precisa, anche nel foglio Entrate.
A28: 5. | C28: Ogni settimana (o mese) incolla i movimenti PostePay nel foglio Movimenti, aggiungendo a mano quelli EdenRed.
A29: 6. | C29: Torna qui. Due minuti in tutto.
A31: Perché funziona | C31: Non misura le spese ma il patrimonio: patrimonio di domenica scorsa + entrate − patrimonio di oggi = quanto è uscito, contanti e buoni pasto compresi. Per lo stesso motivo il bonifico al conto risparmio non risulta come spesa: sposta i soldi da una tasca all'altra.
A33: Legenda | C33: Blu = celle che scrivi tu. Nero = formule, non toccarle. Corsivo blu = previsione non ancora confermata (fogli Spese/Entrate). Giallo (foglio Piano) = parametri da rivedere se cambia il piano.

Sheet Settimane
A1: Il quaderno dei 5.000 — registro settimanale
A2: Ogni domenica scrivi solo le colonne in blu: i saldi letti dalle app (banca, contanti contati a mente, buoni pasto residui) e le entrate della settimana. Tutto il resto si calcola da solo. Budget previsto: scrivi prima quanto pensi di spendere, così a fine settimana vedi lo scarto reale. La prima riga in corsivo è un esempio: cancellala.
A3: Domenica | B3: Conto corrente (€) | C3: Conto risparmio (€) | D3: Contanti (€) | E3: Buoni pasto (€) | F3: Entrate (€) | G3: Nota | H3: Patrimonio (€) | I3: Speso in settimana (€) | J3: Budget previsto (€) | K3: Scarto vs budget (€)
A4: 46264 | B4: 2190 | C4: 0 | D4: 0 | E4: 0 | F4: 2190 | G4: ESEMPIO — stipendio di agosto (cancella questa riga) | H4: =IF(NOT(ISNUMBER($A4)),"",$B4+$C4+$D4+$E4) | I4: =IF(OR(NOT(ISNUMBER($A4)),NOT(ISNUMBER($A3))),"",$H3+$F4-$H4) | K4: =IF(OR($I4="",$J4=""),"",$I4-$J4)
A5: 46285 | B5: 74 | C5: 470 | D5: 350 | E5: 81 | F5: 0 | G5: Rinnovo caldaia (140 € — vedi foglio Spese) | H5: =IF(NOT(ISNUMBER($A5)),"",$B5+$C5+$D5+$E5) | I5: =IF(OR(NOT(ISNUMBER($A5)),NOT(ISNUMBER($A4))),"",$H4+$F5-$H5) | K5: =IF(OR($I5="",$J5=""),"",$I5-$J5)
F6: 0 | H6: =IF(NOT(ISNUMBER($A6)),"",$B6+$C6+$D6+$E6) | I6: =IF(OR(NOT(ISNUMBER($A6)),NOT(ISNUMBER($A5))),"",$H5+$F6-$H6) | K6: =IF(OR($I6="",$J6=""),"",$I6-$J6)
F7: 0 | H7: =IF(NOT(ISNUMBER($A7)),"",$B7+$C7+$D7+$E7) | I7: =IF(OR(NOT(ISNUMBER($A7)),NOT(ISNUMBER($A6))),"",$H6+$F7-$H7) | K7: =IF(OR($I7="",$J7=""),"",$I7-$J7)
F8: 0 | H8: =IF(NOT(ISNUMBER($A8)),"",$B8+$C8+$D8+$E8) | I8: =IF(OR(NOT(ISNUMBER($A8)),NOT(ISNUMBER($A7))),"",$H7+$F8-$H8) | K8: =IF(OR($I8="",$J8=""),"",$I8-$J8)
F9: 0 | H9: =IF(NOT(ISNUMBER($A9)),"",$B9+$C9+$D9+$E9) | I9: =IF(OR(NOT(ISNUMBER($A9)),NOT(ISNUMBER($A8))),"",$H8+$F9-$H9) | K9: =IF(OR($I9="",$J9=""),"",$I9-$J9)
F10: 0 | H10: =IF(NOT(ISNUMBER($A10)),"",$B10+$C10+$D10+$E10) | I10: =IF(OR(NOT(ISNUMBER($A10)),NOT(ISNUMBER($A9))),"",$H9+$F10-$H10) | K10: =IF(OR($I10="",$J10=""),"",$I10-$J10)
F11: 0 | H11: =IF(NOT(ISNUMBER($A11)),"",$B11+$C11+$D11+$E11) | I11: =IF(OR(NOT(ISNUMBER($A11)),NOT(ISNUMBER($A10))),"",$H10+$F11-$H11) | K11: =IF(OR($I11="",$J11=""),"",$I11-$J11)
F12: 0 | H12: =IF(NOT(ISNUMBER($A12)),"",$B12+$C12+$D12+$E12) | I12: =IF(OR(NOT(ISNUMBER($A12)),NOT(ISNUMBER($A11))),"",$H11+$F12-$H12) | K12: =IF(OR($I12="",$J12=""),"",$I12-$J12)
F13: 0 | H13: =IF(NOT(ISNUMBER($A13)),"",$B13+$C13+$D13+$E13) | I13: =IF(OR(NOT(ISNUMBER($A13)),NOT(ISNUMBER($A12))),"",$H12+$F13-$H13) | K13: =IF(OR($I13="",$J13=""),"",$I13-$J13)
F14: 0 | H14: =IF(NOT(ISNUMBER($A14)),"",$B14+$C14+$D14+$E14) | I14: =IF(OR(NOT(ISNUMBER($A14)),NOT(ISNUMBER($A13))),"",$H13+$F14-$H14) | K14: =IF(OR($I14="",$J14=""),"",$I14-$J14)
F15: 0 | H15: =IF(NOT(ISNUMBER($A15)),"",$B15+$C15+$D15+$E15) | I15: =IF(OR(NOT(ISNUMBER($A15)),NOT(ISNUMBER($A14))),"",$H14+$F15-$H15) | K15: =IF(OR($I15="",$J15=""),"",$I15-$J15)
F16: 0 | H16: =IF(NOT(ISNUMBER($A16)),"",$B16+$C16+$D16+$E16) | I16: =IF(OR(NOT(ISNUMBER($A16)),NOT(ISNUMBER($A15))),"",$H15+$F16-$H16) | K16: =IF(OR($I16="",$J16=""),"",$I16-$J16)
F17: 0 | H17: =IF(NOT(ISNUMBER($A17)),"",$B17+$C17+$D17+$E17) | I17: =IF(OR(NOT(ISNUMBER($A17)),NOT(ISNUMBER($A16))),"",$H16+$F17-$H17) | K17: =IF(OR($I17="",$J17=""),"",$I17-$J17)
... F203: 0 | H203: =IF(NOT(ISNUMBER($A203)),"",$B203+$C203+$D203+$E203) | I203: =IF(OR(NOT(ISNUMBER($A203)),NOT(ISNUMBER($A202))),"",$H202+$F203-$H203) | K203: =IF(OR($I203="",$J203=""),"",$I203-$J203)

Sheet Spese
A1: Spese annuali — quello che esce dal buffer
A2: Il buffer si riempie da solo di 150 € al mese. Qui registri solo le uscite grosse: assicurazione, caldaia, bollo, gomme, revisione, tagliando. Le righe in corsivo blu sono previsioni (non ancora accadute): correggile o cancellale quando la spesa è reale.
A3: Data | B3: Voce | C3: Importo (€)
A4: 46285 | B4: Revisione caldaia + controllo fumi (100 € contanti + 40 € carta) | C4: 140
A5: 46298 | B5: Assicurazione auto — rinnovo Prima/Triglav, pagamento unico | C5: 467.76
A6: 46300 | B6: Lotta Club Seggiano — quota iscrizione + primo mese, MENSILE non semestrale (corretto): dal secondo mese 25 €/mese ricorrenti, va nel budget fisso non più qui. 2 allenamenti/settimana per ora. | C6: 50
B105: Totale speso dal buffer | C105: =SUM($C$4:$C$103)

Sheet Entrate
A1: Entrate — stipendi, contributi, rimborsi
A2: Registra qui ogni entrata importante, per sapere sempre da dove viene ogni euro. Le righe in corsivo blu sono previsioni (non ancora arrivate): correggile con l'importo vero appena arrivano, o cancellale se saltano.
A3: Data | B3: Voce | C3: Importo (€)
A4: 46294 | B4: Stipendio di settembre — accreditato, confermato | C4: 2197
A5: 46296 | B5: Bonifico da papà (previsto) | C5: 250
A6: 46296 | B6: Ricarica buoni pasto — 22 giorni lavorativi × 9 € (previsto) | C6: 198
A7: 46341 | B7: Rimborso 730 — accredito su carta (atteso nov/dic, importo confermato dal 730-3) | C7: 1481
A8: 46357 | B8: Tredicesima 2026 — 5/12 da assunzione 03/08/2026, netto stimato dal cedolino di agosto (previsto) | C8: 800
B105: Totale entrate registrate | C105: =SUM($C$4:$C$103)

Sheet Movimenti
A1: Movimenti PostePay + buoni pasto — dati grezzi
A2: Nessuna formula qui dentro: è solo un elenco. Le somme e i confronti li fai tu, come vuoi. Importo è sempre positivo: la direzione (spesa o accredito) è nella colonna Tipo, così non ti tocca fare i conti con il segno meno. Per aggiungere una categoria nuova basta scriverla — non c'è nulla da rompere. Il raggruppamento per data e categoria te lo preparo io in chat ogni volta che incolli i movimenti nuovi: tu li copi qui sotto così come sono.
A4: Data | B4: Descrizione | C4: Importo (€) | D4: Tipo | E4: Categoria
A5: 46272 | B5: PostePay — ricarica per attivazione nuova carta (saldo trasferito dalla vecchia) | C5: 980.1 | D5: Accredito | E5: Trasferimento
A6: 46272 | B6: EdenRed — ricarica 21 buoni pasto | C6: 189 | D6: Accredito | E6: Entrata
A7: 46275 | B7: PostePay — POS 46084 San Donato (benzina) | C7: 26.3 | D7: Spesa | E7: Benzina
A8: 46277 | B8: PostePay — POS Market San Donato | C8: 4.14 | D8: Spesa | E8: Cibo
A9: 46277 | B9: PostePay — POS Ipercoop Peschiera Borromeo | C9: 7.57 | D9: Spesa | E9: Cibo
A10: 46278 | B10: PostePay — POS Scotti Andrea, Mediglia (Cascina de Lassi, Landriano — carne) | C10: 46 | D10: Spesa | E10: Cibo
A11: 46278 | B11: PostePay — commissioni PagoPA | C11: 1.5 | D11: Spesa | E11: Bollette
A12: 46278 | B12: PostePay — avviso PagoPA, Ente 06655971007 | C12: 137.49 | D12: Spesa | E12: Bollette
A13: 46279 | B13: PostePay — commissioni PagoPA | C13: 1.5 | D13: Spesa | E13: Bollette
A14: 46279 | B14: PostePay — avviso PagoPA, Ente 06655971007 | C14: 84.76 | D14: Spesa | E14: Bollette
A15: 46279 | B15: PostePay — POS Esselunga San Giuliano Milanese | C15: 1.95 | D15: Spesa | E15: Cibo
A16: 46279 | B16: EdenRed — Essselunga (buono pasto) | C16: 9 | D16: Spesa | E16: Cibo
... A28: 46284 | B28: EdenRed — 2 movimenti non dettagliati (4 buoni pasto) | C28: 36 | D28: Spesa | E28: Cibo
A30: Note | B30: «Trasferimento» = spostamenti fra tuoi conti/chiusura BCC Caravaggio: non sono spesa reale, tienile fuori dai tuoi conteggi di spesa. Le 4 ricariche buoni pasto del 19/09 non erano nello screenshot: importo dedotto da 21 caricati − 9 rimasti − gli 8 già visti = 4.

Sheet Piano
A1: Parametri e curva del piano
A2: Le celle gialle sono i parametri: cambiali se cambia il piano.
A3: Obiettivo del fondo (€) | B3: 5000 | C3: Fondo di emergenza: circa 3 mesi di spese essenziali.
A4: Accantonamento buffer al mese (€) | B4: 150 | C4: Assicurazione, bollo, freni, gomme, revisione.
A5: Inizio accantonamento buffer | B5: 46266 | C5: Primo mese in cui hai messo via i 150 €.
A7: Impegni noti, pagati dal conto corrente (non dal fondo)
C8: • Assicurazione auto: 467,76 € a inizio ottobre (confermato, vedi foglio Spese).
C9: • Lotta Club Seggiano: 50 € a ottobre (iscrizione + primo mese), poi 25 €/mese ricorrenti — è mensile, non semestrale (corretto). Da novembre è un costo fisso ricorrente, non più una spesa una tantum del buffer.
C10: • Rimborso 730: 1.481 € netti attesi nov/dic (vedi foglio Entrate). Non ancora nella curva sotto: la aggiungo quando arriva davvero.
A11: Data | B11: Fondo (€) | C11: Da dove viene
A12: 46266 | B12: 0 | C12: Punto di partenza.
A13: 46285 | B13: 470 | C13: Saldo reale letto dal foglio Settimane il 20/09.
A14: 46326 | B14: 1020 | C14: 470 + 550 € versati a ottobre (deciso il 20/09). Assicurazione e lotta escono dal conto corrente, non dal fondo: non riducono questo numero.
A16: Da novembre in poi | C16: Non ancora stimato: manca la conferma se il tuo stipendio netto "a regime" e i 250 € di tuo padre sono ricorrenti o solo di ottobre, e quando arriva davvero il rimborso 730. Appena hai il primo dato reale di novembre (foglio Settimane), aggiungo il punto qui invece di indovinarlo adesso.
A18: Fonte dei numeri | C18: Piano concordato il 13/09/2026. Curva rifatta il 20/09/2026 dopo un errore: la versione precedente non era stata ricalcolata con i costi reali di caldaia, assicurazione e lotta, e contava la lotta come rata mensile mentre è un pagamento semestrale unico.
